{"comments":[{"address":"scratch_area!C5","id":"{BB0165F5-9129-4CD4-A3F1-809813FDC58F}","content":"Gives a indication of the momentum of prices throughout the year, absent base effects","authorEmail":"alexholmes@eiu.com","authorName":"Alex Holmes","creationDate":"2025-07-05T11:53:10Z","replies":null},{"address":"Custom_scratch_area!A1","id":"{07468F47-EAB5-4747-9212-C6B58628A780}","content":" Gives a indication of the momentum of prices throughout the year, absent base effects","authorEmail":"alexholmes@eiu.com","authorName":"Alex Holmes","creationDate":"2025-07-11T06:24:32Z","replies":null}]}